Text_Preprocessing_Toolkit/TPT.py
Text_Preprocessing_Toolkit/__init__.py
Text_Preprocessing_Toolkit-0.0.2.dist-info/METADATA
Text_Preprocessing_Toolkit-0.0.2.dist-info/WHEEL
Text_Preprocessing_Toolkit-0.0.2.dist-info/top_level.txt
Text_Preprocessing_Toolkit-0.0.2.dist-info/RECORD
