Metadata-Version: 2.1
Name: Text_Preprocessing_Toolkit
Version: 0.0.2
Summary: A package that automates text preprocessing
Home-page: https://github.com/Gaurav-Jaiswal-1/Text-Preprocessing-Toolkit.git
Author: Gaurav Jaiswal
Author-email: Gaurav Jaiswal <jaiswalgaurav863@gmail.com>
License: MIT
Project-URL: Homepage, https://github.com/Gaurav-Jaiswal-1/Text-Preprocessing-Toolkit
Project-URL: Issues, https://github.com/Gaurav-Jaiswal-1/Text-Preprocessing-Toolkit/issues
Keywords: text preprocessing,toolkit,automation
Classifier: Development Status :: 3 - Alpha
Classifier: Programming Language :: Python :: 3.8
Classifier: Programming Language :: Python :: 3.9
Classifier: Programming Language :: Python :: 3.10
Classifier: Programming Language :: Python :: 3.11
Classifier: License :: OSI Approved :: MIT License
Classifier: Operating System :: OS Independent
Requires-Python: >=3.8
Requires-Dist: spellchecker
Requires-Dist: matplotlib
Requires-Dist: pandas
Requires-Dist: spacy
Requires-Dist: nltk
